runmany/__init__.py
runmany/default_settings.json
runmany/parser.py
runmany/py.typed
runmany/runmany.py
runmany/runner.py
runmany/settings.py
runmany/util.py
runmany-2.3.0.dist-info/LICENSE.txt
runmany-2.3.0.dist-info/METADATA
runmany-2.3.0.dist-info/WHEEL
runmany-2.3.0.dist-info/entry_points.txt
runmany-2.3.0.dist-info/top_level.txt
runmany-2.3.0.dist-info/RECORD
