Metadata-Version: 2.1
Name: runmany
Version: 2.3.0
Summary: A tool to run many programs written in many languages from one file.
Home-page: https://github.com/discretegames/runmany
Author: discretegames
Author-email: discretizedgames@gmail.com
License: MIT
Project-URL: GitHub, https://github.com/discretegames/runmany
Project-URL: PyPI, https://pypi.org/project/runmany
Project-URL: VSCode Extension, https://marketplace.visualstudio.com/items?itemName=discretegames.runmany
Keywords: run,many,runmany,execute,other languages,multiple languages,manyfile,.many,one file,programs,chrestomathy,polyglot
Platform: UNKNOWN
Classifier: Development Status :: 5 - Production/Stable
Classifier: Intended Audience :: Education
Classifier: Intended Audience :: Developers
Classifier: License :: OSI Approved :: MIT License
Classifier: Topic :: Software Development :: Interpreters
Classifier: Topic :: Software Development :: Compilers
Classifier: Topic :: Software Development :: Build Tools
Classifier: Topic :: Utilities
Classifier: Typing :: Typed
Classifier: Programming Language :: Python :: 3
Classifier: Programming Language :: Python :: 3.6
Classifier: Programming Language :: Python :: 3.7
Classifier: Programming Language :: Python :: 3.8
Classifier: Programming Language :: Python :: 3.9
Classifier: Programming Language :: Python :: 3.10
Requires-Python: >=3.6
License-File: LICENSE.txt
